LICENSE
MANIFEST.in
README.rst
setup.py
pybible/Bible.py
pybible/Chapters.py
pybible/Indices.py
pybible/__init__.py
pybible/engine.py
pybible/functions.py
pybible/pure.py
pybible/search.py
pybible/simple.py
pybible.egg-info/PKG-INFO
pybible.egg-info/SOURCES.txt
pybible.egg-info/dependency_links.txt
pybible.egg-info/top_level.txt