Metadata-Version: 1.1
Name: pybible
Version: 0.0.1
Summary: Bible search functions developed on the go.
Home-page: http://davidcheong.co/
Author: David Cheong
Author-email: davidcheong@hotmail.com
License: MIT
Platform: UNKNOWN
Classifier: License :: The MIT License
Classifier: Operating System :: OS Independent
Classifier: Intended Audience :: Developers
Classifier: Programming Language :: Python
Classifier: Programming Language :: Python :: 3
Classifier: Programming Language :: Python :: 3.2
Classifier: Programming Language :: Python :: 3.3
Classifier: Programming Language :: Python :: 3.4
